<?xml version="1.0" encoding="us-ascii"?>
<Catalog>
    <CLight id="Storm_Portrait_Gazlowe_Scifi" parent="default">
        <ToDInfoArray index="0">
            <Id value="Storm_Portrait_Gazlowe_Scifi"/>
            <AmbientColor value="0.239216,0.203922,0.352941"/>
            <OperatorHDR value="4"/>
            <Colorize value="1"/>
            <Param index="HDRExposure" value="1.650000"/>
            <Param index="HDRBloomThreshold" value="0.900000"/>
            <Param index="HDRWhitePoint" value="1.850000"/>
            <Param index="TerrainSpecularExp" value="73.000000"/>
            <Param index="CreepSpecularExp" value="30.000000"/>
            <Param index="CreepHDRSpecMultiplier" value="3.000000"/>
            <Param index="ColorizationInputHigh" value="0.975000"/>
            <Param index="ColorizationBlend" value="0.000000"/>
            <DirectionalLight index="Key">
                <Color value="1.000000,0.819608,0.400000"/>
                <ColorMultiplier value="4.000000"/>
                <SpecularColor value="0.909804,0.909804,1.000000"/>
                <SpecColorMultiplier value="1.303000"/>
                <Direction value="-0.982032,0.157120,0.104528"/>
            </DirectionalLight>
            <DirectionalLight index="Fill" Color="0.686275,1.000000,0.670588" ColorMultiplier="1.400000" Direction="0.808656,-0.233865,0.539800"/>
            <DirectionalLight index="Back" Color="0.976471,0.211765,0.101961" ColorMultiplier="0.600000" Direction="-0.153681,0.984761,0.081417"/>
        </ToDInfoArray>
        <EditorCategories value="LightGroup:PortraitsUnitsOther"/>
    </CLight>
    <CModel id="GazloweSkinScifi" parent="HeroTinker">
        <Model value="Assets\Units\Heroes\Storm_Hero_Gazlowe_Scifi\Storm_Hero_Gazlowe_Scifi.m3"/>
        <TextureDeclares Prefix="Storm_Hero_Gazlowe_Scifi" Slot="main"/>
    </CModel>
    <CModel id="GazloweSkinScifiDeathRagdoll" parent="HeroDeathRagdoll">
        <Model value="Assets\Units\Heroes\Storm_Hero_Gazlowe_Scifi_DeathRagdoll\Storm_Hero_Gazlowe_Scifi_DeathRagdoll.m3"/>
        <TextureDeclares Prefix="Storm_Hero_Gazlowe_Scifi" Slot="main"/>
    </CModel>
    <CModel id="GazloweSkinScifiPortraitAddition" parent="TinkerPortraitAddition">
        <Model value="Assets\Units\Heroes\Storm_Hero_Gazlowe_Scifi\Storm_Hero_Gazlowe_Scifi.m3"/>
        <TextureDeclares Prefix="Storm_Hero_Gazlowe_Scifi" Slot="main"/>
    </CModel>
    <CModel id="GazloweSkinScifiPortrait" parent="HeroesPortrait">
        <Model value="Assets\Portraits\Storm_Portrait_Gazlowe_Base_Background\Storm_Portrait_Gazlowe_Base_Background.m3"/>
        <Lighting value="Storm_Portrait_Gazlowe_Scifi"/>
    </CModel>
    <CModel id="GazloweSkinScifiRoboGoblin" parent="HeroTinkerRobot">
        <Model value="Assets\Units\Heroes\Storm_Morph_Gazlowe_Scifi_RoboGoblin\Storm_Morph_Gazlowe_Scifi_RoboGoblin.m3"/>
        <TextureDeclares Prefix="Storm_Hero_Gazlowe_Scifi" Slot="main"/>
    </CModel>
    <CModel id="GazloweSkinScifiRoboGoblinDeathRagdoll" parent="HeroDeathRagdoll">
        <Model value="Assets\Units\Heroes\Storm_Morph_Gazlowe_Scifi_RoboGoblin_DeathRagdoll\Storm_Morph_Gazlowe_Scifi_RoboGoblin_DeathRagdoll.m3"/>
        <TextureDeclares Prefix="Storm_Hero_Gazlowe_Scifi" Slot="main"/>
    </CModel>
    <CModel id="DethLazorChargeUpModel1SciFi" parent="DethLazorChargeUpModel1">
        <Model value="Assets\Effects\Storm_FX_Gazlowe_SciFi_DethLazor_Cast\Storm_FX_Gazlowe_SciFi_DethLazor_Cast.m3"/>
    </CModel>
    <CModel id="GazloweSkinScifiRockitTurretOneBarrelDeath" parent="TinkerRockItTurretDeath">
        <Model value="Assets\Units\Pets\Storm_Pet_GazloweTurret_Scifi_Death\Storm_Pet_GazloweTurret_Scifi_Death.m3"/>
    </CModel>
    <CModel id="GazloweSkinScifiRockitTurretOneBarrelTimeout" parent="RockItTurretDeathTimeout">
        <Model value="Assets\Units\Pets\Storm_Pet_GazloweTurret_Scifi_Timeout\Storm_Pet_GazloweTurret_Scifi_Timeout.m3"/>
    </CModel>
    <CModel id="GazloweSkinScifiRockitTurretThreeBarrelDeath" parent="TinkerRockItTurretDeath">
        <Model value="Assets\Units\Pets\Storm_Pet_GazloweTurret_Scifi_TB_Death\Storm_Pet_GazloweTurret_Scifi_TB_Death.m3"/>
    </CModel>
    <CModel id="GazloweSkinScifiRockitTurretThreeBarrelTimeout" parent="RockItTurretDeathTimeout">
        <Model value="Assets\Units\Pets\Storm_Pet_GazloweTurret_Scifi_TB_Timeout\Storm_Pet_GazloweTurret_Scifi_TB_Timeout.m3"/>
    </CModel>
    <CModel id="StormFXGazloweSciFiDethLazor" parent="OneShotSpellFX">
        <Model value="Assets\Effects\Storm_FX_Gazlowe_SciFi_DethLazor\Storm_FX_Gazlowe_SciFi_DethLazor.m3"/>
    </CModel>
    <CModel id="StormFXGazloweSciFiDethLazorFreezeRay" parent="OneShotSpellFX">
        <Model value="Assets\Effects\Storm_FX_Gazlowe_SciFi_DethLazor_FreezeRay\Storm_FX_Gazlowe_SciFi_DethLazor_FreezeRay.m3"/>
    </CModel>
    <CModel id="GazloweRockItTurrentSciFiPlacement" parent="TinkerRockItTurretPlacement">
        <Model value="Assets\Units\Pets\Storm_Pet_GazloweTurret_Scifi\Storm_Pet_GazloweTurret_Scifi.m3"/>
    </CModel>
    <CModel id="GazloweRockItTurretAttackImpactSciFi" parent="TinkerRockItTurretAttackImpact">
        <Model value="Assets\Effects\Storm_FX_Gazlowe_SciFi_TurretMissile_Impact\Storm_FX_Gazlowe_SciFi_TurretMissile_Impact.m3"/>
    </CModel>
    <CModel id="GazloweRockItTurretAttackImpactSlowSciFi" parent="TinkerRockItTurretAttackImpactSlow">
        <Model value="Assets\Effects\Storm_FX_Gazlowe_SciFi_TurretMissile_Slow_Impact\Storm_FX_Gazlowe_SciFi_TurretMissile_Slow_Impact.m3"/>
    </CModel>
    <CModel id="GazloweRockItTurretMissileSciFi" parent="TinkerRockItTurretMissile">
        <Model value="Assets\Effects\Storm_FX_Gazlowe_SciFi_TurretMissile\Storm_FX_Gazlowe_SciFi_TurretMissile.m3"/>
    </CModel>
    <CModel id="GazloweRockItTurretMissileSlowSciFi" parent="TinkerRockItTurretMissileSlow">
        <Model value="Assets\Effects\Storm_FX_Gazlowe_SciFi_TurretMissile_Slow\Storm_FX_Gazlowe_SciFi_TurretMissile_Slow.m3"/>
    </CModel>
    <CModel id="GazloweRockItTurretSideMissileSciFi" parent="RockItTurretRelicSideMissile">
        <Model value="Assets\Effects\Storm_FX_Gazlowe_SciFi_TurretMissile\Storm_FX_Gazlowe_SciFi_TurretMissile.m3"/>
    </CModel>
    <CModel id="GazloweRockItTurretSciFi" parent="TinkerRockItTurret">
        <Model value="Assets\Units\Pets\Storm_Pet_GazloweTurret_Scifi\Storm_Pet_GazloweTurret_Scifi.m3"/>
        <RequiredAnims index="0" removed="1"/>
    </CModel>
    <CModel id="GazloweSkinScifiRockitTurretSalvage" parent="RockItTurretSalvage">
        <Model value="Assets\Units\Pets\Storm_Pet_GazloweTurret_Scifi_Death\Storm_Pet_GazloweTurret_Scifi_Death.m3"/>
    </CModel>
    <CModel id="GazloweSkinScifiRockitTurretThreeBarrelsSalvage" parent="RockItTurretThreeBarrelSalvage">
        <Model value="Assets\Units\Pets\Storm_Pet_GazloweTurret_Scifi_TB_Death\Storm_Pet_GazloweTurret_Scifi_TB_Death.m3"/>
    </CModel>
    <CRewardIcon id="GazloweScifi" parent="BattlePayRewardParent">
        <License value="17928"/>
    </CRewardIcon>
    <CSkin default="1" id="GazloweScifiCommon">
        <ReplacementArray Catalog="Model" From="HeroTinker" To="GazloweSkinScifi"/>
        <ReplacementArray Catalog="Model" From="TinkerPortrait" To="GazloweSkinScifiPortrait"/>
        <ReplacementArray Catalog="Model" From="TinkerPortraitAddition" To="GazloweSkinScifiPortraitAddition"/>
        <ReplacementArray Catalog="Actor" From="TinkerPortrait" To="GazloweSkinScifiPortrait"/>
        <ReplacementArray Catalog="Model" From="HeroTinkerDeathRagdoll" To="GazloweSkinScifiDeathRagdoll"/>
        <ReplacementArray Catalog="Model" From="HeroTinkerRobot" To="GazloweSkinScifiRoboGoblin"/>
        <ReplacementArray Catalog="Model" From="HeroTinkerRoboGoblinDeathRagdoll" To="GazloweSkinScifiRoboGoblinDeathRagdoll"/>
        <ReplacementArray Catalog="Model" From="TinkerRoboGoblinMorphModel" To="GazloweRoboGoblinScifiMorphModel"/>
        <ReplacementArray Catalog="Model" From="TinkerDethLazorBeam" To="StormFXGazloweSciFiDethLazor"/>
        <ReplacementArray Catalog="Model" From="TinkerDethLazorFirinMahLazorzTalentBeam" To="StormFXGazloweSciFiDethLazor"/>
        <ReplacementArray Catalog="Model" From="TinkerDethLazorBeamEZFreezy" To="StormFXGazloweSciFiDethLazorFreezeRay"/>
        <ReplacementArray Catalog="Model" From="DethLazorChargeUpModel1" To="DethLazorChargeUpModel1SciFi"/>
        <ReplacementArray Catalog="Model" From="TinkerRockItTurret" To="GazloweRockItTurretSciFi"/>
        <ReplacementArray Catalog="Model" From="TinkerRockItTurretPlacement" To="GazloweRockItTurrentSciFiPlacement"/>
        <ReplacementArray Catalog="Model" From="TinkerRockItTurretMissile" To="GazloweRockItTurretMissileSciFi"/>
        <ReplacementArray Catalog="Model" From="TinkerRockItTurretAttackImpact" To="GazloweRockItTurretAttackImpactSciFi"/>
        <ReplacementArray Catalog="Model" From="TinkerRockItTurretMissileSlow" To="GazloweRockItTurretMissileSlowSciFi"/>
        <ReplacementArray Catalog="Model" From="TinkerRockItTurretAttackImpactSlow" To="GazloweRockItTurretAttackImpactSlowSciFi"/>
        <ReplacementArray Catalog="Model" From="TinkerRockItTurretDeath" To="GazloweSkinScifiRockitTurretOneBarrelDeath"/>
        <ReplacementArray Catalog="Model" From="RockItTurretDeathTimeout" To="GazloweSkinScifiRockitTurretOneBarrelTimeout"/>
        <ReplacementArray Catalog="Model" From="RockItTurretRelicSideMissile" To="GazloweRockItTurretSideMissileSciFi"/>
        <ReplacementArray Catalog="Model" From="RockItTurretThreeBarrelSalvage" To="GazloweSkinScifiRockitTurretThreeBarrelsSalvage"/>
        <ReplacementArray Catalog="Model" From="RockItTurretSalvage" To="GazloweSkinScifiRockitTurretSalvage"/>
        <ReplacementArray Catalog="Model" From="RockItTurretDeathThreeBarrels" To="GazloweSkinScifiRockitTurretThreeBarrelDeath"/>
        <ReplacementArray Catalog="Model" From="RockItTurretDeathTimeoutThreeBarrels" To="GazloweSkinScifiRockitTurretThreeBarrelTimeout"/>
        <ReplacementArray Catalog="Sound" From="Gazlowe_RockItTurret_Active_Loop" To="Gazlowe_SciFi_RockItTurret_Active_Loop"/>
        <ReplacementArray Catalog="Sound" From="Gazlowe_RockItTurret_AttackImpact" To="Gazlowe_SciFi_RockItTurret_AttackImpact"/>
        <ReplacementArray Catalog="Sound" From="Gazlowe_RockItTurret_AttackLaunch" To="Gazlowe_SciFi_RockItTurret_AttackLaunch"/>
        <ReplacementArray Catalog="Sound" From="Gazlowe_DethLazor_Launch" To="Gazlowe_SciFi_DethLazor_Launch"/>
        <ReplacementArray Catalog="Sound" From="Gazlowe_EZPZ_DimensionalRipper_Launch1" To="Gazlowe_SciFi_EZPZ_DimensionalRipper_Launch1"/>
        <ReplacementArray Catalog="Sound" From="Gazlowe_EZPZ_DimensionalRipper_Launch2" To="Gazlowe_SciFi_EZPZ_DimensionalRipper_Launch2"/>
        <ReplacementArray Catalog="Sound" From="Gazlowe_EZPZ_DimensionalRipper_Launch3" To="Gazlowe_SciFi_EZPZ_DimensionalRipper_Launch3"/>
        <ReplacementArray Catalog="Sound" From="Gazlowe_RoboGoblin_Morph_Cast" To="Gazlowe_SciFi_RoboGoblin_Morph_Cast"/>
        <ReplacementArray Catalog="Sound" From="Gazlowe_RockItTurret_Death" To="Gazlowe_SciFi_RockItTurret_Death"/>
        <ReplacementArray Catalog="Sound" From="Gazlowe_RockItTurret_Destroy" To="Gazlowe_SciFi_RockItTurret_Destroy"/>
        <ReplacementArray Catalog="Sound" From="Gazlowe_DethLazor_Retract" To="StormNoSound"/>
        <ReplacementArray Catalog="Sound" From="Gazlowe_XplodiumBomb_Cast" To="Gazlowe_SciFi_XplodiumBomb_Cast"/>
        <ReplacementArray Catalog="VoiceOver" From="Gazlowe" To="GazloweMartian"/>
        <FeatureArray value="ThemedAbilities"/>
        <FeatureArray value="AlteredVO"/>
        <ReleaseDate Month="5" Day="19" Year="2015"/>
        <DisplayModel value="GazloweSkinScifi"/>
        <ModelGroups Name="GazloweScifiModels">
            <Models value="GazloweSkinScifi"/>
            <Models value="GazloweSkinScifiPortraitAddition"/>
            <Models value="GazloweSkinScifiDeathRagdoll"/>
        </ModelGroups>
        <ModelGroups Name="GazloweScifiRoboGoblinModels">
            <Models value="GazloweSkinScifiRoboGoblin"/>
            <Models value="GazloweSkinScifiRoboGoblinDeathRagdoll"/>
            <Models value="GazloweRoboGoblinScifiMorphModel"/>
        </ModelGroups>
        <VoiceLineArray value="GazloweMartian_VoiceLine01"/>
        <VoiceLineArray value="GazloweMartian_VoiceLine02"/>
        <VoiceLineArray value="GazloweMartian_VoiceLine03"/>
        <VoiceLineArray value="GazloweMartian_VoiceLine04"/>
        <VoiceLineArray value="GazloweMartian_VoiceLine05"/>
        <SortName value="Skin/SortName/GazloweScifiCommonVar1"/>
        <Rarity value="Epic"/>
        <InfoText value="Skin/Info/GazloweScifi"/>
        <VODefinition value="GazloweMartian"/>
        <Universe value="Heroes"/>
    </CSkin>
    <CSkin id="GazloweScifi" parent="GazloweScifiCommon">
        <AttributeId value="GaS1"/>
        <VariationIcon value="Assets\Textures\UI_Glues_Swatch_Yellow_Gray.dds"/>
        <VariationArray value="GazloweScifiOrange"/>
        <VariationArray value="GazloweScifiSilver"/>
        <HyperlinkId value="MadMartianGazlowe"/>
        <SortName value="Skin/SortName/GazloweScifiCommonVar0"/>
        <ProductId value="23229"/>
        <RequiredRewardArray value="GazloweScifi"/>
        <Rarity value="Epic"/>
    </CSkin>
</Catalog>
