<?xml version="1.0" encoding="us-ascii"?>
<Catalog>
    <CActorEventMacroRunnable id="AlexstraszaBaseVar1Macro">
        <Do Send="TextureSelectById Storm_Hero_Alexstrasza_Base_Var1_Diff"/>
        <Do Send="TextureSelectById Storm_Hero_Alexstrasza_Base_Var1_Emis"/>
        <Do Send="TextureSelectById Storm_Hero_Alexstrasza_Base_Var1_Spec"/>
    </CActorEventMacroRunnable>
    <CActorEventMacroRunnable id="AlexstraszaDragonBaseVar1Macro">
        <Do Send="TextureSelectById Storm_Morph_AlexstraszaDragon_Base_Var1_Diff"/>
        <Do Send="TextureSelectById Storm_Morph_AlexstraszaDragon_Base_Var1_Emis"/>
        <Do Send="TextureSelectById Storm_Morph_AlexstraszaDragon_Base_Var1_Spec"/>
    </CActorEventMacroRunnable>
    <CLight id="Storm_Portrait_Alexstrasza_Base_Var1" parent="default">
        <ToDInfoArray index="0" Id="Storm_Portrait_Alexstrasza_Base_Var1" OperatorHDR="4" Colorize="1">
            <AmbientColor value="0.360784,0.262745,0.262745" X="0.360784" Y="0.262745" Z="0.262745"/>
            <Param index="HDRExposure" value="1.650000"/>
            <Param index="HDRBloomThreshold" value="0.900000"/>
            <Param index="HDRWhitePoint" value="1.850000"/>
            <Param index="TerrainSpecularExp" value="73.000000"/>
            <Param index="CreepSpecularExp" value="30.000000"/>
            <Param index="CreepHDRSpecMultiplier" value="3.000000"/>
            <Param index="ColorizationInputHigh" value="0.975000"/>
            <Param index="ColorizationBlend" value="0.000000"/>
            <DirectionalLight index="Key" ColorMultiplier="1.250000" SpecColorMultiplier="2.000000">
                <Color value="0.627451,0.823529,0.882353" X="0.627451" Y="0.823529" Z="0.882353"/>
                <SpecularColor value="0.921569,0.921569,1.000000" X="0.921569" Y="0.921569"/>
                <Direction value="-0.709406,0.496732,-0.500000" X="-0.709406" Y="0.496732" Z="-0.500000"/>
            </DirectionalLight>
            <DirectionalLight index="Fill" ColorMultiplier="0.750000">
                <Color value="0.803922,0.529412,0.333333" X="0.803922" Y="0.529412" Z="0.333333"/>
                <Direction value="0.742404,0.346189,-0.573577" X="0.742404" Y="0.346189" Z="-0.573577"/>
            </DirectionalLight>
            <DirectionalLight index="Back" ColorMultiplier="3.500000">
                <Color value="0.137255,0.823529,0.509804" X="0.137255" Y="0.823529" Z="0.509804"/>
                <Direction value="-0.719846,-0.604023,0.342020" X="-0.719846" Y="-0.604023" Z="0.342020"/>
            </DirectionalLight>
        </ToDInfoArray>
        <EditorCategories value="LightGroup:PortraitsUnitsOther"/>
    </CLight>
    <CLight id="Storm_Portrait_AlexstraszaDragon_Base_Var1" parent="default">
        <ToDInfoArray index="0" Id="Storm_Portrait_AlexstraszaDragon_Base_Var1" OperatorHDR="4" Colorize="1">
            <AmbientColor value="0.360784,0.262745,0.262745" X="0.360784" Y="0.262745" Z="0.262745"/>
            <Param index="HDRExposure" value="1.650000"/>
            <Param index="HDRBloomThreshold" value="0.900000"/>
            <Param index="HDRWhitePoint" value="1.850000"/>
            <Param index="TerrainSpecularExp" value="73.000000"/>
            <Param index="CreepSpecularExp" value="30.000000"/>
            <Param index="CreepHDRSpecMultiplier" value="3.000000"/>
            <Param index="ColorizationInputHigh" value="0.975000"/>
            <Param index="ColorizationBlend" value="0.000000"/>
            <DirectionalLight index="Key" ColorMultiplier="1.250000" SpecColorMultiplier="2.000000">
                <Color value="0.490196,0.784314,0.490196" X="0.490196" Y="0.784314" Z="0.490196"/>
                <SpecularColor value="0.921569,0.921569,1.000000" X="0.921569" Y="0.921569"/>
                <Direction value="-0.709406,0.496732,-0.500000" X="-0.709406" Y="0.496732" Z="-0.500000"/>
            </DirectionalLight>
            <DirectionalLight index="Fill" ColorMultiplier="0.850000">
                <Color value="0.274510,0.568627,0.725490" X="0.274510" Y="0.568627" Z="0.725490"/>
                <Direction value="0.851651,0.397131,-0.342020" X="0.851651" Y="0.397131" Z="-0.342020"/>
            </DirectionalLight>
            <DirectionalLight index="Back" ColorMultiplier="5.000000">
                <Color value="0.098039,0.568627,0.352941" X="0.098039" Y="0.568627" Z="0.352941"/>
                <Direction value="-0.852869,-0.492404,0.173648" X="-0.852869" Y="-0.492404" Z="0.173648"/>
            </DirectionalLight>
        </ToDInfoArray>
        <EditorCategories value="LightGroup:PortraitsUnitsOther"/>
    </CLight>
    <CModel id="AlexstraszaVar1Portrait" parent="AlexstraszaPortraitCommon">
        <Lighting value="Storm_Portrait_Alexstrasza_Base_Var1"/>
    </CModel>
    <CModel id="AlexstraszaDragonVar1Portrait" parent="AlexstraszaDragonPortraitCommon">
        <Lighting value="Storm_Portrait_AlexstraszaDragon_Base_Var1"/>
    </CModel>
    <CSkin id="AlexstraszaBaseVar1" parent="AlexstraszaBaseCommon">
        <AttributeId value="Ale0"/>
        <ProductId value="99999"/>
        <RequiredRewardArray value="Alexstrasza"/>
        <ModelMacroRun Models="AlexstraszaBaseModels" Macro="AlexstraszaBaseVar1Macro"/>
        <ModelMacroRun Models="AlexstraszaDragonBaseModels" Macro="AlexstraszaDragonBaseVar1Macro"/>
        <ReplacementArray Catalog="Model" From="AlexstraszaPortrait" To="AlexstraszaVar1Portrait"/>
        <ReplacementArray Catalog="Model" From="AlexstraszaDragonPortrait" To="AlexstraszaDragonVar1Portrait"/>
        <HyperlinkId value="SaroniteAlexstrasza"/>
    </CSkin>
    <CTexture id="Storm_Hero_Alexstrasza_Base_Var1_Diff" parent="MainSlotTexture"/>
    <CTexture id="Storm_Hero_Alexstrasza_Base_Var1_Emis" parent="MainSlotTexture"/>
    <CTexture id="Storm_Hero_Alexstrasza_Base_Var1_Spec" parent="MainSlotTexture"/>
    <CTexture id="Storm_Morph_AlexstraszaDragon_Base_Var1_Diff" parent="MainSlotTexture"/>
    <CTexture id="Storm_Morph_AlexstraszaDragon_Base_Var1_Emis" parent="MainSlotTexture"/>
    <CTexture id="Storm_Morph_AlexstraszaDragon_Base_Var1_Spec" parent="MainSlotTexture"/>
</Catalog>
