<?xml version="1.0" encoding="us-ascii"?>
<Catalog>
    <CSkin id="ETCUltimateRed" parent="ETCUltimateCommon">
        <AttributeId value="EtcC"/>
        <VariationIcon value="Assets\Textures\ui_glues_swatch_whiteeggshell.dds"/>
        <ModelMacroRun Models="ETCUltimateModels" Macro="ETCUltimateRedMacro"/>
    </CSkin>
    <CTexture id="Storm_Hero_ETC_Ultimate_Red_Diff" parent="MainSlotTexture"/>
    <CTexture id="Storm_Hero_ETC_Ultimate_Red_Emis" parent="MainSlotTexture"/>
    <CTexture id="Storm_Hero_ETC_Ultimate_Red_Spec" parent="MainSlotTexture"/>
    <CActorEventMacroRunnable id="ETCUltimateRedMacro">
        <Do Send="TextureSelectById Storm_Hero_ETC_Ultimate_Red_Diff"/>
        <Do Send="TextureSelectById Storm_Hero_ETC_Ultimate_Red_Emis"/>
        <Do Send="TextureSelectById Storm_Hero_ETC_Ultimate_Red_Spec"/>
    </CActorEventMacroRunnable>
</Catalog>
