<?xml version="1.0" encoding="us-ascii"?>
<Catalog>
    <CActorUnit id="BossHoleSharedVisionUnit" parent="GenericUnitStandard" unitName="BossHoleSharedVisionUnit">
        <Model value="Invisible"/>
        <BuildModel value="Invisible"/>
        <HighlightTooltip value="Unit/Name/Bogus"/>
    </CActorUnit>
    <CActorUnit id="HoleLadderUp">
        <On Terms="Signal.*.MapStart" Send="AnimBaselineStop"/>
        <On Terms="Signal.*.MapStart" Send="AnimBracketStart Cover IGNORE Cover Cover,End 0 1.000000 AsTimeScale"/>
        <On Terms="Signal.*.MinesOpen" Send="AnimBracketStop Cover 0 1.000000 AsTimeScale"/>
        <On Terms="Signal.*.MinesOpen" Send="AnimBracketStart Light Birth Stand {} 0 1.000000 AsTimeScale"/>
        <Remove Terms="Signal.*.MinesOpen" Send="AnimPlay MinesOpen Cover,End PlayForever,NonLooping"/>
    </CActorUnit>
    <CActorUnit id="HoleLadderDown">
        <On Terms="Signal.*.MapStart" Send="AnimBaselineStop"/>
        <On Terms="Signal.*.MapStart" Send="AnimBracketStart Cover IGNORE Cover Cover,End 0 1.000000 AsTimeScale"/>
        <On Terms="Signal.*.MinesOpen" Send="AnimBracketStop Cover 0 1.000000 AsTimeScale"/>
        <On Terms="Signal.*.MinesOpen" Send="AnimBracketStart Light Birth Stand {} 0 1.000000 AsTimeScale"/>
        <Remove Terms="Signal.*.MinesOpen" Send="AnimPlay MinesOpen Cover,End PlayForever,NonLooping"/>
    </CActorUnit>
    <CActorUnit id="KingsCore">
        <Model value="NecroCore"/>
        <DeathArray index="Normal" SoundLink="Doodad_Necro_Core_Death"/>
        <DeathCustoms ModelLink="NecroCoreDeathModel" SoundLink="Doodad_Necro_Core_Death" Name="Variation0"/>
        <On Terms="ActorCreation" Send="SetShowStatusBar"/>
        <On Terms="AssetPreInit" Send="ModelLinkCustomize NecroCoreBirthModel"/>
        <On Terms="AnimDone; AnimName CoreStart" Send="ModelSwap NecroCore"/>
        <On Terms="AnimDone; AnimName CoreStart" Send="AnimSetTime ::Baseline"/>
        <On Terms="AnimDone; AnimName CoreStart" Send="SetShowStatusBar 1"/>
        <On Terms="UnitDeathCustomize" Send="DeathCustomize Variation0"/>
    </CActorUnit>
    <CActorUnit id="UnderworldMinion">
        <MinimapIcon value=""/>
    </CActorUnit>
    <CActorUnit id="UnderworldRangedMinion">
        <MinimapIcon value=""/>
    </CActorUnit>
    <CActorUnit id="UnderworldBoss">
        <On Terms="ActorCreation" Send="$Birth NonLooping -1.000000 -1.000000 1.000000 AsTimeScale"/>
    </CActorUnit>
    <CActorUnit id="UnderworldSummonedBoss">
        <On Terms="ActorCreation" Send="$Birth NonLooping -1.000000 -1.000000 1.000000 AsTimeScale"/>
    </CActorUnit>
</Catalog>
