<?xml version="1.0" encoding="us-ascii"?>
<Catalog>
    <CActorEventMacroRunnable id="ArtanisPurifierRedMacro">
        <EditorCategories value=""/>
        <Do Send="TextureSelectById Storm_Hero_Artanis_Purifier_Red_Diff"/>
        <Do Send="TextureSelectById Storm_Hero_Artanis_Purifier_Red_Emis"/>
        <Do Send="TextureSelectById Storm_Hero_Artanis_Purifier_Red_Spec"/>
    </CActorEventMacroRunnable>
    <CRewardIcon id="ArtanisPurifierRed" parent="BattlePayRewardParent">
        <License value="18060"/>
    </CRewardIcon>
    <CSkin id="ArtanisPurifierRed" parent="ArtanisPurifierCommon">
        <AttributeId value="Rtn5"/>
        <VariationIcon value="Assets\Textures\ui_glues_swatch_red_bright.dds"/>
        <ModelMacroRun Models="ArtanisPurifierModels" Macro="ArtanisPurifierRedMacro"/>
        <ProductId value="23361"/>
        <RequiredRewardArray value="ArtanisPurifierRed"/>
        <HyperlinkId value="CrimsonPurifierArtanis"/>
        <Rarity value="Rare"/>
    </CSkin>
    <CTexture id="Storm_Hero_Artanis_Purifier_Red_Diff" parent="MainSlotTexture"/>
    <CTexture id="Storm_Hero_Artanis_Purifier_Red_Spec" parent="MainSlotTexture"/>
    <CTexture id="Storm_Hero_Artanis_Purifier_Red_Emis" parent="MainSlotTexture"/>
</Catalog>
